MANIFEST.in
README.rst
setup.py
automationserver/__init__.py
automationserver/main.py
automationserver/server.py
cli/__init__.py
cli/client.py
cli/main.py
fieldagent/__init__.py
fieldagent/common.py
fieldagent/devicemanager.py
fieldagent/main.py
fieldagent/rpc.py
fieldagent/version.py
hedgehog_fa.egg-info/PKG-INFO
hedgehog_fa.egg-info/SOURCES.txt
hedgehog_fa.egg-info/dependency_links.txt
hedgehog_fa.egg-info/entry_points.txt
hedgehog_fa.egg-info/not-zip-safe
hedgehog_fa.egg-info/requires.txt
hedgehog_fa.egg-info/top_level.txt