Metadata-Version: 1.1
Name: hedgehog-fa
Version: 0.15
Summary: Stationcontroller services.
Home-page: http://github.com/lordoftheflies/hedgehog-fa
Author: lordoftheflies
Author-email: heglas11@gmail.com
License: MIT
Keywords: funniest joke comedy flying circus
Platform: UNKNOWN
Classifier: Development Status :: 3 - Alpha
Classifier: License :: OSI Approved :: MIT License
Classifier: Programming Language :: Python :: 2.7
Classifier: Topic :: Text Processing :: Linguistic
